<?xml version="1.0" encoding="UTF-8" standalone="no" ?>
<LEGOPrimitive versionMajor="1" versionMinor="0">
  <Annotations>
    <Annotation aliases="15086"/>
    <Annotation designname="ARMOUR 3 W/ 3X CORED KNOB"/>
    <Annotation maingroupid="253"/>
    <Annotation maingroupname="FIGURE ACCESSORIES, UPPER BODY"/>
    <Annotation platformid="200"/>
    <Annotation platformname="SYSTEM"/>
    <Annotation version="2"/>
  </Annotations>
  <Collision>
    <Box sX="0.628029" sY="0.04507" sZ="0.217858" angle="0" ax="0" ay="1" az="0" tx="0" ty="0.06493" tz="-0.477788"/>
    <Box sX="0.633585" sY="0.04507" sZ="0.143785" angle="0" ax="0" ay="1" az="0" tx="0" ty="0.06493" tz="0.403715"/>
    <Box sX="0.320285" sY="0.04507" sZ="0.35976" angle="0" ax="0" ay="1" az="0" tx="0.582785" ty="0.06493" tz="-0.02381"/>
    <Box sX="0.320285" sY="0.04507" sZ="0.35976" angle="0" ax="0" ay="1" az="0" tx="1.21356" ty="0.288064" tz="-0.02381"/>
    <Box sX="0.320285" sY="0.039746" sZ="0.35976" angle="120" ax="0.57735" ay="0.57735" az="0.57735" tx="0.944886" ty="-0.158349" tz="-0.46365"/>
    <Box sX="0.186457" sY="0.04507" sZ="0.35976" angle="90" ax="0" ay="0" az="1" tx="0.806348" ty="0.252585" tz="-0.02381"/>
    <Box sX="0.282403" sY="0.04507" sZ="0.35976" angle="83.10447" ax="0.344078" ay="0.48163" az="0.806004" tx="0.554997" ty="0.311039" tz="-0.507294"/>
    <Box sX="0.282403" sY="0.04507" sZ="0.297272" angle="91.44582" ax="0.493282" ay="0.567638" az="0.659135" tx="0.290946" ty="0.31939" tz="-0.726458"/>
    <Box sX="0.127764" sY="0.062907" sZ="0.426567" angle="120" ax="0.57735" ay="0.57735" az="0.57735" tx="0" ty="-0.634502" tz="0.484593"/>
    <Box sX="0.202285" sY="0.062907" sZ="0.781465" angle="120" ax="0.57735" ay="0.57735" az="0.57735" tx="0" ty="-0.284453" tz="0.484593"/>
    <Box sX="0.353948" sY="0.04507" sZ="0.781465" angle="120" ax="0.57735" ay="0.57735" az="0.57735" tx="0" ty="-0.436116" tz="-0.49723"/>
    <Box sX="0.320285" sY="0.04507" sZ="0.35976" angle="180" ax="0" ay="1" az="0" tx="-0.582785" ty="0.06493" tz="-0.02381"/>
    <Box sX="0.320285" sY="0.039592" sZ="0.35976" angle="120" ax="0.57735" ay="0.57735" az="0.57735" tx="-0.944886" ty="-0.158349" tz="-0.463804"/>
    <Box sX="0.320285" sY="0.04507" sZ="0.35976" angle="180" ax="0" ay="1" az="0" tx="-1.21356" ty="0.288064" tz="-0.02381"/>
    <Box sX="0.282403" sY="0.04507" sZ="0.297272" angle="132.04057" ax="0.516502" ay="0.764077" az="0.386539" tx="-0.290946" ty="0.31939" tz="-0.726458"/>
    <Box sX="0.282403" sY="0.04507" sZ="0.35976" angle="142.73863" ax="0.564189" ay="0.789735" az="0.240849" tx="-0.554997" ty="0.311039" tz="-0.507294"/>
    <Box sX="0.273396" sY="0.028021" sZ="0.35976" angle="135.92413" ax="0.414296" ay="0.709359" az="0.570235" tx="0.823087" ty="-0.091989" tz="0.433711"/>
    <Box sX="0.273396" sY="0.028021" sZ="0.35976" angle="97.7764" ax="0.701555" ay="0.498017" az="0.509705" tx="-0.823087" ty="-0.091989" tz="0.433711"/>
  </Collision>
  <Connectivity>
    <Custom2DField type="23" width="2" height="2" angle="90" ax="1" ay="0" az="0" tx="-0.4" ty="0" tz="0.5575">
      29:0,29:0,29:0,
      29:0,1:4:34,29:0,
      29:0,29:0,29:0
    </Custom2DField>
    <Custom2DField type="23" width="2" height="2" angle="90" ax="-1" ay="0" az="0" tx="-0.8" ty="-0.8" tz="-0.5523">
      29:0,29:0,29:0,
      29:0,1:4:34,29:0,
      29:0,29:0,29:0
    </Custom2DField>
    <Custom2DField type="23" width="2" height="2" angle="90" ax="-1" ay="0" az="0" tx="0" ty="-0.8" tz="-0.5523">
      29:0,29:0,29:0,
      29:0,1:4:34,29:0,
      29:0,29:0,29:0
    </Custom2DField>
    <Custom2DField type="22" width="2" height="2" angle="0" ax="0" ay="1" az="0" tx="-0.4" ty="0" tz="-0.4">
      29:0,29:0,29:0,
      29:0,15:4:33,29:0,
      29:0,29:0,29:0
    </Custom2DField>
    <Fixed type="30" axes="2" angle="180" ax="0" ay="1" az="0" tx="0.3" ty="0" tz="0"/>
    <Custom2DField type="22" width="2" height="2" angle="180" ax="0" ay="0" az="1" tx="0.4" ty="0.12" tz="-0.4">
      29:0,29:0,29:0,
      29:0,15:4:33,29:0,
      29:0,29:0,29:0
    </Custom2DField>
    <Fixed type="30" axes="2" angle="0" ax="0" ay="1" az="0" tx="-0.3" ty="0" tz="0"/>
  </Connectivity>
  <PhysicsAttributes inertiaTensor="0.431955,0,0,0,1.04408,0,0,0,0.991308" centerOfMass="0,-0.045891,-0.118195" mass="1" frictionType="0"/>
  <Bounding>
    <AABB minX="-1.55085" minY="-0.800064" minZ="-0.970889" maxX="1.55085" maxY="0.708281" maxZ="0.7345"/>
  </Bounding>
  <GeometryBounding>
    <AABB minX="-1.55085" minY="-0.800064" minZ="-0.970889" maxX="1.55085" maxY="0.708281" maxZ="0.7345"/>
  </GeometryBounding>
</LEGOPrimitive>
