<?xml version="1.0" encoding="UTF-8" standalone="no" ?>
<LEGOPrimitive versionMajor="1" versionMinor="0">
  <Annotations>
    <Annotation aliases="18601"/>
    <Annotation designname="PLATE 12X24 W/ 6X6, ROUND CUTOUT"/>
    <Annotation maingroupid="215"/>
    <Annotation maingroupname="PLATES"/>
    <Annotation platformid="200"/>
    <Annotation platformname="SYSTEM"/>
    <Annotation version="1"/>
  </Annotations>
  <Collision>
    <Box sX="3.58581" sY="0.15" sZ="2.39" angle="0" ax="0" ay="1" az="0" tx="3.19581" ty="0.16" tz="-2"/>
    <Box sX="9.59" sY="0.15" sZ="1.59386" angle="0" ax="0" ay="1" az="0" tx="9.2" ty="0.16" tz="-1.20386"/>
    <Box sX="1.18581" sY="0.15" sZ="4.79" angle="0" ax="0" ay="1" az="0" tx="5.59581" ty="0.16" tz="-4.4"/>
    <Box sX="4.79" sY="0.15" sZ="0.793858" angle="0" ax="0" ay="1" az="0" tx="9.2" ty="0.16" tz="-8.39614"/>
    <Box sX="1.18581" sY="0.15" sZ="4.79" angle="0" ax="0" ay="1" az="0" tx="12.80419" ty="0.16" tz="-4.4"/>
    <Box sX="3.58581" sY="0.15" sZ="2.39" angle="0" ax="0" ay="1" az="0" tx="15.20419" ty="0.16" tz="-2"/>
    <Box sX="0.22524" sY="0.15" sZ="0.22524" angle="45" ax="0" ay="1" az="0" tx="10.8" ty="0.16" tz="-2.79732"/>
    <Box sX="0.22524" sY="0.15" sZ="0.22524" angle="45" ax="0" ay="1" az="0" tx="11.6" ty="0.16" tz="-3.60268"/>
    <Box sX="0.22524" sY="0.15" sZ="0.22524" angle="45" ax="0" ay="1" az="0" tx="7.6" ty="0.16" tz="-2.80268"/>
    <Box sX="0.22524" sY="0.15" sZ="0.22524" angle="45" ax="0" ay="1" az="0" tx="6.8" ty="0.16" tz="-3.60268"/>
    <Box sX="0.072545" sY="0.15" sZ="0.238733" angle="135" ax="0" ay="-1" az="0" tx="10.93616" ty="0.16" tz="-6.93616"/>
    <Box sX="0.495167" sY="0.045" sZ="1.14768" angle="135" ax="0" ay="-1" az="0" tx="11.25452" ty="0.265" tz="-7.21548"/>
    <Box sX="0.072545" sY="0.15" sZ="0.238733" angle="45" ax="0" ay="-1" az="0" tx="7.46384" ty="0.16" tz="-6.93616"/>
    <Box sX="0.495167" sY="0.045" sZ="1.14768" angle="45" ax="0" ay="-1" az="0" tx="7.18453" ty="0.265" tz="-7.25452"/>
    <Box sX="0.072545" sY="0.15" sZ="0.238733" angle="45" ax="0" ay="1" az="0" tx="7.46384" ty="0.16" tz="-3.46384"/>
    <Box sX="0.495167" sY="0.045" sZ="1.14768" angle="45" ax="0" ay="1" az="0" tx="7.14548" ty="0.265" tz="-3.18453"/>
    <Box sX="0.072545" sY="0.15" sZ="0.238733" angle="135" ax="0" ay="1" az="0" tx="10.93616" ty="0.16" tz="-3.46384"/>
    <Box sX="0.495167" sY="0.045" sZ="1.14768" angle="135" ax="0" ay="1" az="0" tx="11.21547" ty="0.265" tz="-3.14548"/>
    <Box sX="0.22524" sY="0.15" sZ="0.22524" angle="45" ax="0" ay="1" az="0" tx="7.6" ty="0.16" tz="-7.60268"/>
    <Box sX="0.22524" sY="0.15" sZ="0.22524" angle="45" ax="0" ay="1" az="0" tx="6.8" ty="0.16" tz="-6.80268"/>
    <Box sX="0.22524" sY="0.15" sZ="0.22524" angle="45" ax="0" ay="1" az="0" tx="10.8" ty="0.16" tz="-7.60268"/>
    <Box sX="0.22524" sY="0.15" sZ="0.22524" angle="45" ax="0" ay="1" az="0" tx="11.6" ty="0.16" tz="-6.80268"/>
  </Collision>
  <Connectivity>
    <Custom2DField type="23" width="48" height="24" angle="0" ax="0" ay="1" az="0" tx="-0.4" ty="0.32" tz="-9.2">
      29:0,29:0,29:0,29:0,29:0,29:0,29:0,29:0,29:0,29:0,29:0,29:0,18:1:1,23:4:1,18:2:1,23:4:1,18:2:1,23:4:1,18:2:1,23:4:1,18:2:1,23:4:1,18:2:1,23:4:1,18:2:1,23:4:1,18:2:1,23:4:1,18:2:1,23:4:1,18:2:1,23:4:1,18:2:1,23:4:1,18:2:1,23:4:1,18:1:1,29:0,29:0,29:0,29:0,29:0,29:0,29:0,29:0,29:0,29:0,29:0,29:0,
      29:0,29:0,29:0,29:0,29:0,29:0,29:0,29:0,29:0,29:0,29:0,29:0,23:4:1,0:4:1,23:4:1,0:4:1,23:4:1,0:4:1,23:4:1,0:4:1,23:4:1,0:4:1,23:4:1,0:4:1,23:4:1,0:4:1,23:4:1,0:4:1,23:4:1,0:4:1,23:4:1,0:4:1,23:4:1,0:4:1,23:4:1,0:4:1,23:4:1,29:0,29:0,29:0,29:0,29:0,29:0,29:0,29:0,29:0,29:0,29:0,29:0,
      29:0,29:0,29:0,29:0,29:0,29:0,29:0,29:0,29:0,29:0,29:0,29:0,18:2:1,23:4:1,18:4:1,23:4:1,18:4:1,23:4:1,18:4:1,23:4:1,18:4:1,23:4:1,18:4:1,23:4:1,18:4:1,23:4:1,18:4:1,23:4:1,18:4:1,23:4:1,18:4:1,23:4:1,18:4:1,23:4:1,18:4:1,23:4:1,18:2:1,29:0,29:0,29:0,29:0,29:0,29:0,29:0,29:0,29:0,29:0,29:0,29:0,
      29:0,29:0,29:0,29:0,29:0,29:0,29:0,29:0,29:0,29:0,29:0,29:0,23:4:1,0:4:1,23:4:1,0:4:1,23:4:1,0:4:1,23:4:1,0:4:1,23:4:1,0:4:1,23:4:1,0:4:1,23:4:1,0:4:1,23:4:1,0:4:1,23:4:1,0:4:1,23:4:1,0:4:1,23:4:1,0:4:1,23:4:1,0:4:1,23:4:1,29:0,29:0,29:0,29:0,29:0,29:0,29:0,29:0,29:0,29:0,29:0,29:0,
      29:0,29:0,29:0,29:0,29:0,29:0,29:0,29:0,29:0,29:0,29:0,29:0,18:2:1,23:4:1,18:4:1,23:4:1,18:4:1,23:4:1,18:4:1,23:4:1,18:4:1,23:4:1,29:0,29:0,29:0,29:0,29:0,23:4:1,18:4:1,23:4:1,18:4:1,23:4:1,18:4:1,23:4:1,18:4:1,23:4:1,18:2:1,29:0,29:0,29:0,29:0,29:0,29:0,29:0,29:0,29:0,29:0,29:0,29:0,
      29:0,29:0,29:0,29:0,29:0,29:0,29:0,29:0,29:0,29:0,29:0,29:0,23:4:1,0:4:1,23:4:1,0:4:1,23:4:1,0:4:1,23:4:1,0:4:1,29:0,29:0,29:0,29:0,29:0,29:0,29:0,29:0,29:0,0:4:1,23:4:1,0:4:1,23:4:1,0:4:1,23:4:1,0:4:1,23:4:1,29:0,29:0,29:0,29:0,29:0,29:0,29:0,29:0,29:0,29:0,29:0,29:0,
      29:0,29:0,29:0,29:0,29:0,29:0,29:0,29:0,29:0,29:0,29:0,29:0,18:2:1,23:4:1,18:4:1,23:4:1,18:4:1,23:4:1,18:4:1,29:0,29:0,29:0,29:0,29:0,29:0,29:0,29:0,29:0,29:0,29:0,18:4:1,23:4:1,18:4:1,23:4:1,18:4:1,23:4:1,18:2:1,29:0,29:0,29:0,29:0,29:0,29:0,29:0,29:0,29:0,29:0,29:0,29:0,
      29:0,29:0,29:0,29:0,29:0,29:0,29:0,29:0,29:0,29:0,29:0,29:0,23:4:1,0:4:1,23:4:1,0:4:1,23:4:1,0:4:1,23:4:1,29:0,29:0,29:0,29:0,29:0,29:0,29:0,29:0,29:0,29:0,29:0,23:4:1,0:4:1,23:4:1,0:4:1,23:4:1,0:4:1,23:4:1,29:0,29:0,29:0,29:0,29:0,29:0,29:0,29:0,29:0,29:0,29:0,29:0,
      29:0,29:0,29:0,29:0,29:0,29:0,29:0,29:0,29:0,29:0,29:0,29:0,18:2:1,23:4:1,18:4:1,23:4:1,18:4:1,23:4:1,29:0,29:0,29:0,29:0,29:0,29:0,29:0,29:0,29:0,29:0,29:0,29:0,29:0,23:4:1,18:4:1,23:4:1,18:4:1,23:4:1,18:2:1,29:0,29:0,29:0,29:0,29:0,29:0,29:0,29:0,29:0,29:0,29:0,29:0,
      29:0,29:0,29:0,29:0,29:0,29:0,29:0,29:0,29:0,29:0,29:0,29:0,23:4:1,0:4:1,23:4:1,0:4:1,23:4:1,0:4:1,29:0,29:0,29:0,29:0,29:0,29:0,29:0,29:0,29:0,29:0,29:0,29:0,29:0,0:4:1,23:4:1,0:4:1,23:4:1,0:4:1,23:4:1,29:0,29:0,29:0,29:0,29:0,29:0,29:0,29:0,29:0,29:0,29:0,29:0,
      29:0,29:0,29:0,29:0,29:0,29:0,29:0,29:0,29:0,29:0,29:0,29:0,18:2:1,23:4:1,18:4:1,23:4:1,18:4:1,23:4:1,29:0,29:0,29:0,29:0,29:0,29:0,29:0,29:0,29:0,29:0,29:0,29:0,29:0,23:4:1,18:4:1,23:4:1,18:4:1,23:4:1,18:2:1,29:0,29:0,29:0,29:0,29:0,29:0,29:0,29:0,29:0,29:0,29:0,29:0,
      29:0,29:0,29:0,29:0,29:0,29:0,29:0,29:0,29:0,29:0,29:0,29:0,23:4:1,0:4:1,23:4:1,0:4:1,23:4:1,0:4:1,29:0,29:0,29:0,29:0,29:0,29:0,29:0,29:0,29:0,29:0,29:0,29:0,29:0,0:4:1,23:4:1,0:4:1,23:4:1,0:4:1,23:4:1,29:0,29:0,29:0,29:0,29:0,29:0,29:0,29:0,29:0,29:0,29:0,29:0,
      18:1:1,23:4:1,18:2:1,23:4:1,18:2:1,23:4:1,18:2:1,23:4:1,18:2:1,23:4:1,18:2:1,23:4:1,18:3:1,23:4:1,18:4:1,23:4:1,18:4:1,23:4:1,29:0,29:0,29:0,29:0,29:0,29:0,29:0,29:0,29:0,29:0,29:0,29:0,29:0,23:4:1,18:4:1,23:4:1,18:4:1,23:4:1,18:3:1,23:4:1,18:2:1,23:4:1,18:2:1,23:4:1,18:2:1,23:4:1,18:2:1,23:4:1,18:2:1,23:4:1,18:1:1,
      23:4:1,0:4:1,23:4:1,0:4:1,23:4:1,0:4:1,23:4:1,0:4:1,23:4:1,0:4:1,23:4:1,0:4:1,23:4:1,0:4:1,23:4:1,0:4:1,23:4:1,0:4:1,23:4:1,29:0,29:0,29:0,29:0,29:0,29:0,29:0,29:0,29:0,29:0,29:0,23:4:1,0:4:1,23:4:1,0:4:1,23:4:1,0:4:1,23:4:1,0:4:1,23:4:1,0:4:1,23:4:1,0:4:1,23:4:1,0:4:1,23:4:1,0:4:1,23:4:1,0:4:1,23:4:1,
      18:2:1,23:4:1,18:4:1,23:4:1,18:4:1,23:4:1,18:4:1,23:4:1,18:4:1,23:4:1,18:4:1,23:4:1,18:4:1,23:4:1,18:4:1,23:4:1,18:4:1,23:4:1,18:4:1,29:0,29:0,29:0,29:0,29:0,29:0,29:0,29:0,29:0,29:0,29:0,18:4:1,23:4:1,18:4:1,23:4:1,18:4:1,23:4:1,18:4:1,23:4:1,18:4:1,23:4:1,18:4:1,23:4:1,18:4:1,23:4:1,18:4:1,23:4:1,18:4:1,23:4:1,18:2:1,
      23:4:1,0:4:1,23:4:1,0:4:1,23:4:1,0:4:1,23:4:1,0:4:1,23:4:1,0:4:1,23:4:1,0:4:1,23:4:1,0:4:1,23:4:1,0:4:1,23:4:1,0:4:1,23:4:1,0:4:1,29:0,29:0,29:0,29:0,29:0,29:0,29:0,29:0,29:0,0:4:1,23:4:1,0:4:1,23:4:1,0:4:1,23:4:1,0:4:1,23:4:1,0:4:1,23:4:1,0:4:1,23:4:1,0:4:1,23:4:1,0:4:1,23:4:1,0:4:1,23:4:1,0:4:1,23:4:1,
      18:2:1,23:4:1,18:4:1,23:4:1,18:4:1,23:4:1,18:4:1,23:4:1,18:4:1,23:4:1,18:4:1,23:4:1,18:4:1,23:4:1,18:4:1,23:4:1,18:4:1,23:4:1,18:4:1,23:4:1,18:4:1,23:4:1,29:0,29:0,29:0,29:0,29:0,23:4:1,18:4:1,23:4:1,18:4:1,23:4:1,18:4:1,23:4:1,18:4:1,23:4:1,18:4:1,23:4:1,18:4:1,23:4:1,18:4:1,23:4:1,18:4:1,23:4:1,18:4:1,23:4:1,18:4:1,23:4:1,18:2:1,
      23:4:1,0:4:1,23:4:1,0:4:1,23:4:1,0:4:1,23:4:1,0:4:1,23:4:1,0:4:1,23:4:1,0:4:1,23:4:1,0:4:1,23:4:1,0:4:1,23:4:1,0:4:1,23:4:1,0:4:1,23:4:1,0:4:1,23:4:1,0:4:1,23:4:1,0:4:1,23:4:1,0:4:1,23:4:1,0:4:1,23:4:1,0:4:1,23:4:1,0:4:1,23:4:1,0:4:1,23:4:1,0:4:1,23:4:1,0:4:1,23:4:1,0:4:1,23:4:1,0:4:1,23:4:1,0:4:1,23:4:1,0:4:1,23:4:1,
      18:2:1,23:4:1,18:4:1,23:4:1,18:4:1,23:4:1,18:4:1,23:4:1,18:4:1,23:4:1,18:4:1,23:4:1,18:4:1,23:4:1,18:4:1,23:4:1,18:4:1,23:4:1,18:4:1,23:4:1,18:4:1,23:4:1,18:4:1,23:4:1,18:4:1,23:4:1,18:4:1,23:4:1,18:4:1,23:4:1,18:4:1,23:4:1,18:4:1,23:4:1,18:4:1,23:4:1,18:4:1,23:4:1,18:4:1,23:4:1,18:4:1,23:4:1,18:4:1,23:4:1,18:4:1,23:4:1,18:4:1,23:4:1,18:2:1,
      23:4:1,0:4:1,23:4:1,0:4:1,23:4:1,0:4:1,23:4:1,0:4:1,23:4:1,0:4:1,23:4:1,0:4:1,23:4:1,0:4:1,23:4:1,0:4:1,23:4:1,0:4:1,23:4:1,0:4:1,23:4:1,0:4:1,23:4:1,0:4:1,23:4:1,0:4:1,23:4:1,0:4:1,23:4:1,0:4:1,23:4:1,0:4:1,23:4:1,0:4:1,23:4:1,0:4:1,23:4:1,0:4:1,23:4:1,0:4:1,23:4:1,0:4:1,23:4:1,0:4:1,23:4:1,0:4:1,23:4:1,0:4:1,23:4:1,
      18:2:1,23:4:1,18:4:1,23:4:1,18:4:1,23:4:1,18:4:1,23:4:1,18:4:1,23:4:1,18:4:1,23:4:1,18:4:1,23:4:1,18:4:1,23:4:1,18:4:1,23:4:1,18:4:1,23:4:1,18:4:1,23:4:1,18:4:1,23:4:1,18:4:1,23:4:1,18:4:1,23:4:1,18:4:1,23:4:1,18:4:1,23:4:1,18:4:1,23:4:1,18:4:1,23:4:1,18:4:1,23:4:1,18:4:1,23:4:1,18:4:1,23:4:1,18:4:1,23:4:1,18:4:1,23:4:1,18:4:1,23:4:1,18:2:1,
      23:4:1,0:4:1,23:4:1,0:4:1,23:4:1,0:4:1,23:4:1,0:4:1,23:4:1,0:4:1,23:4:1,0:4:1,23:4:1,0:4:1,23:4:1,0:4:1,23:4:1,0:4:1,23:4:1,0:4:1,23:4:1,0:4:1,23:4:1,0:4:1,23:4:1,0:4:1,23:4:1,0:4:1,23:4:1,0:4:1,23:4:1,0:4:1,23:4:1,0:4:1,23:4:1,0:4:1,23:4:1,0:4:1,23:4:1,0:4:1,23:4:1,0:4:1,23:4:1,0:4:1,23:4:1,0:4:1,23:4:1,0:4:1,23:4:1,
      18:2:1,23:4:1,18:4:1,23:4:1,18:4:1,23:4:1,18:4:1,23:4:1,18:4:1,23:4:1,18:4:1,23:4:1,18:4:1,23:4:1,18:4:1,23:4:1,18:4:1,23:4:1,18:4:1,23:4:1,18:4:1,23:4:1,18:4:1,23:4:1,18:4:1,23:4:1,18:4:1,23:4:1,18:4:1,23:4:1,18:4:1,23:4:1,18:4:1,23:4:1,18:4:1,23:4:1,18:4:1,23:4:1,18:4:1,23:4:1,18:4:1,23:4:1,18:4:1,23:4:1,18:4:1,23:4:1,18:4:1,23:4:1,18:2:1,
      23:4:1,0:4:1,23:4:1,0:4:1,23:4:1,0:4:1,23:4:1,0:4:1,23:4:1,0:4:1,23:4:1,0:4:1,23:4:1,0:4:1,23:4:1,0:4:1,23:4:1,0:4:1,23:4:1,0:4:1,23:4:1,0:4:1,23:4:1,0:4:1,23:4:1,0:4:1,23:4:1,0:4:1,23:4:1,0:4:1,23:4:1,0:4:1,23:4:1,0:4:1,23:4:1,0:4:1,23:4:1,0:4:1,23:4:1,0:4:1,23:4:1,0:4:1,23:4:1,0:4:1,23:4:1,0:4:1,23:4:1,0:4:1,23:4:1,
      18:1:1,23:4:1,18:2:1,23:4:1,18:2:1,23:4:1,18:2:1,23:4:1,18:2:1,23:4:1,18:2:1,23:4:1,18:2:1,23:4:1,18:2:1,23:4:1,18:2:1,23:4:1,18:2:1,23:4:1,18:2:1,23:4:1,18:2:1,23:4:1,18:2:1,23:4:1,18:2:1,23:4:1,18:2:1,23:4:1,18:2:1,23:4:1,18:2:1,23:4:1,18:2:1,23:4:1,18:2:1,23:4:1,18:2:1,23:4:1,18:2:1,23:4:1,18:2:1,23:4:1,18:2:1,23:4:1,18:2:1,23:4:1,18:1:1
    </Custom2DField>
    <Custom2DField type="22" width="48" height="24" angle="0" ax="0" ay="1" az="0" tx="-0.4" ty="0" tz="-9.2">
      29:0,29:0,29:0,29:0,29:0,29:0,29:0,29:0,29:0,29:0,29:0,29:0,22:1:1,22:2:1,22:2:1,22:2:1,22:2:1,22:2:1,22:2:1,22:2:1,22:2:1,22:2:1,22:2:1,22:2:1,22:2:1,22:2:1,22:2:1,22:2:1,22:2:1,22:2:1,22:2:1,22:2:1,22:2:1,22:2:1,22:2:1,22:2:1,22:1:1,29:0,29:0,29:0,29:0,29:0,29:0,29:0,29:0,29:0,29:0,29:0,29:0,
      29:0,29:0,29:0,29:0,29:0,29:0,29:0,29:0,29:0,29:0,29:0,29:0,22:2:1,15:4:1,23:4:1,15:4:1,22:2:1,15:4:1,23:4:1,15:4:1,22:2:1,15:4:1,23:4:1,15:4:1,22:2:1,15:4:1,23:4:1,15:4:1,22:2:1,15:4:1,23:4:1,15:4:1,22:2:1,15:4:1,23:4:1,15:4:1,22:2:1,29:0,29:0,29:0,29:0,29:0,29:0,29:0,29:0,29:0,29:0,29:0,29:0,
      29:0,29:0,29:0,29:0,29:0,29:0,29:0,29:0,29:0,29:0,29:0,29:0,22:2:1,23:4:1,7:4:2,23:4:1,22:2:1,23:4:1,7:4:2,23:4:1,22:2:1,23:4:1,7:4:2,23:4:1,22:2:1,23:4:1,7:4:2,23:4:1,22:2:1,23:4:1,7:4:2,23:4:1,22:2:1,23:4:1,7:4:2,23:4:1,22:2:1,29:0,29:0,29:0,29:0,29:0,29:0,29:0,29:0,29:0,29:0,29:0,29:0,
      29:0,29:0,29:0,29:0,29:0,29:0,29:0,29:0,29:0,29:0,29:0,29:0,22:2:1,15:4:1,23:4:1,15:4:1,22:2:1,15:4:1,23:4:1,15:4:1,22:2:1,15:4:1,23:4:1,15:4:1,22:2:1,15:4:1,23:4:1,15:4:1,22:2:1,15:4:1,23:4:1,15:4:1,22:2:1,15:4:1,23:4:1,15:4:1,22:2:1,29:0,29:0,29:0,29:0,29:0,29:0,29:0,29:0,29:0,29:0,29:0,29:0,
      29:0,29:0,29:0,29:0,29:0,29:0,29:0,29:0,29:0,29:0,29:0,29:0,22:2:1,22:2:1,22:2:1,22:2:1,8:4:2,22:2:1,22:2:1,22:2:1,8:4:2,22:2:1,22:2:1,22:2:1,22:2:1,22:2:1,22:2:1,22:2:1,8:4:2,22:2:1,22:2:1,22:2:1,8:4:2,22:2:1,22:2:1,22:2:1,22:2:1,29:0,29:0,29:0,29:0,29:0,29:0,29:0,29:0,29:0,29:0,29:0,29:0,
      29:0,29:0,29:0,29:0,29:0,29:0,29:0,29:0,29:0,29:0,29:0,29:0,22:2:1,15:4:1,23:4:1,15:4:1,22:2:1,15:4:1,23:4:1,15:4:1,22:2:1,29:0,29:0,29:0,29:0,29:0,29:0,29:0,22:2:1,15:4:1,23:4:1,15:4:1,22:2:1,15:4:1,23:4:1,15:4:1,22:2:1,29:0,29:0,29:0,29:0,29:0,29:0,29:0,29:0,29:0,29:0,29:0,29:0,
      29:0,29:0,29:0,29:0,29:0,29:0,29:0,29:0,29:0,29:0,29:0,29:0,22:2:1,23:4:1,7:4:2,23:4:1,22:2:1,23:4:1,7:4:2,22:2:1,29:0,29:0,29:0,29:0,29:0,29:0,29:0,29:0,29:0,22:2:1,7:4:2,23:4:1,22:2:1,23:4:1,7:4:2,23:4:1,22:2:1,29:0,29:0,29:0,29:0,29:0,29:0,29:0,29:0,29:0,29:0,29:0,29:0,
      29:0,29:0,29:0,29:0,29:0,29:0,29:0,29:0,29:0,29:0,29:0,29:0,22:2:1,15:4:1,23:4:1,15:4:1,22:2:1,15:4:1,23:4:1,29:0,29:0,29:0,29:0,29:0,29:0,29:0,29:0,29:0,29:0,29:0,23:4:1,15:4:1,22:2:1,15:4:1,23:4:1,15:4:1,22:2:1,29:0,29:0,29:0,29:0,29:0,29:0,29:0,29:0,29:0,29:0,29:0,29:0,
      29:0,29:0,29:0,29:0,29:0,29:0,29:0,29:0,29:0,29:0,29:0,29:0,22:2:1,22:2:1,22:2:1,22:2:1,8:4:2,22:2:1,22:2:1,29:0,29:0,29:0,29:0,29:0,29:0,29:0,29:0,29:0,29:0,29:0,22:2:1,22:2:1,8:4:2,22:2:1,22:2:1,22:2:1,22:2:1,29:0,29:0,29:0,29:0,29:0,29:0,29:0,29:0,29:0,29:0,29:0,29:0,
      29:0,29:0,29:0,29:0,29:0,29:0,29:0,29:0,29:0,29:0,29:0,29:0,22:2:1,15:4:1,23:4:1,15:4:1,22:2:1,15:4:1,22:2:1,29:0,29:0,29:0,29:0,29:0,29:0,29:0,29:0,29:0,29:0,29:0,22:2:1,15:4:1,22:2:1,15:4:1,23:4:1,15:4:1,22:2:1,29:0,29:0,29:0,29:0,29:0,29:0,29:0,29:0,29:0,29:0,29:0,29:0,
      29:0,29:0,29:0,29:0,29:0,29:0,29:0,29:0,29:0,29:0,29:0,29:0,22:2:1,23:4:1,7:4:2,23:4:1,22:2:1,23:4:1,22:2:1,29:0,29:0,29:0,29:0,29:0,29:0,29:0,29:0,29:0,29:0,29:0,22:2:1,23:4:1,22:2:1,23:4:1,7:4:2,23:4:1,22:2:1,29:0,29:0,29:0,29:0,29:0,29:0,29:0,29:0,29:0,29:0,29:0,29:0,
      29:0,29:0,29:0,29:0,29:0,29:0,29:0,29:0,29:0,29:0,29:0,29:0,22:2:1,15:4:1,23:4:1,15:4:1,22:2:1,15:4:1,22:2:1,29:0,29:0,29:0,29:0,29:0,29:0,29:0,29:0,29:0,29:0,29:0,22:2:1,15:4:1,22:2:1,15:4:1,23:4:1,15:4:1,22:2:1,29:0,29:0,29:0,29:0,29:0,29:0,29:0,29:0,29:0,29:0,29:0,29:0,
      22:1:1,22:2:1,22:2:1,22:2:1,22:2:1,22:2:1,22:2:1,22:2:1,22:2:1,22:2:1,22:2:1,22:2:1,22:3:1,22:2:1,22:2:1,22:2:1,8:4:2,22:2:1,22:2:1,29:0,29:0,29:0,29:0,29:0,29:0,29:0,29:0,29:0,29:0,29:0,22:2:1,22:2:1,8:4:2,22:2:1,22:2:1,22:2:1,22:3:1,22:2:1,22:2:1,22:2:1,22:2:1,22:2:1,22:2:1,22:2:1,22:2:1,22:2:1,22:2:1,22:2:1,22:1:1,
      22:2:1,15:4:1,23:4:1,15:4:1,22:2:1,15:4:1,23:4:1,15:4:1,22:2:1,15:4:1,23:4:1,15:4:1,22:2:1,15:4:1,23:4:1,15:4:1,22:2:1,15:4:1,23:4:1,29:0,29:0,29:0,29:0,29:0,29:0,29:0,29:0,29:0,29:0,29:0,23:4:1,15:4:1,22:2:1,15:4:1,23:4:1,15:4:1,22:2:1,15:4:1,23:4:1,15:4:1,22:2:1,15:4:1,23:4:1,15:4:1,22:2:1,15:4:1,23:4:1,15:4:1,22:2:1,
      22:2:1,23:4:1,7:4:2,23:4:1,22:2:1,23:4:1,7:4:2,23:4:1,22:2:1,23:4:1,7:4:2,23:4:1,22:2:1,23:4:1,7:4:2,23:4:1,22:2:1,23:4:1,7:4:2,22:2:1,29:0,29:0,29:0,29:0,29:0,29:0,29:0,29:0,29:0,22:2:1,7:4:2,23:4:1,22:2:1,23:4:1,7:4:2,23:4:1,22:2:1,23:4:1,7:4:2,23:4:1,22:2:1,23:4:1,7:4:2,23:4:1,22:2:1,23:4:1,7:4:2,23:4:1,22:2:1,
      22:2:1,15:4:1,23:4:1,15:4:1,22:2:1,15:4:1,23:4:1,15:4:1,22:2:1,15:4:1,23:4:1,15:4:1,22:2:1,15:4:1,23:4:1,15:4:1,22:2:1,15:4:1,23:4:1,15:4:1,22:2:1,29:0,29:0,29:0,29:0,29:0,29:0,29:0,22:2:1,15:4:1,23:4:1,15:4:1,22:2:1,15:4:1,23:4:1,15:4:1,22:2:1,15:4:1,23:4:1,15:4:1,22:2:1,15:4:1,23:4:1,15:4:1,22:2:1,15:4:1,23:4:1,15:4:1,22:2:1,
      22:2:1,22:2:1,22:2:1,22:2:1,8:4:2,22:2:1,22:2:1,22:2:1,8:4:2,22:2:1,22:2:1,22:2:1,8:4:2,22:2:1,22:2:1,22:2:1,8:4:2,22:2:1,22:2:1,22:2:1,8:4:2,22:2:1,22:2:1,22:2:1,22:2:1,22:2:1,22:2:1,22:2:1,8:4:2,22:2:1,22:2:1,22:2:1,8:4:2,22:2:1,22:2:1,22:2:1,8:4:2,22:2:1,22:2:1,22:2:1,8:4:2,22:2:1,22:2:1,22:2:1,8:4:2,22:2:1,22:2:1,22:2:1,22:2:1,
      22:2:1,15:4:1,23:4:1,15:4:1,22:2:1,15:4:1,23:4:1,15:4:1,22:2:1,15:4:1,23:4:1,15:4:1,22:2:1,15:4:1,23:4:1,15:4:1,22:2:1,15:4:1,23:4:1,15:4:1,22:2:1,15:4:1,23:4:1,15:4:1,22:2:1,15:4:1,23:4:1,15:4:1,22:2:1,15:4:1,23:4:1,15:4:1,22:2:1,15:4:1,23:4:1,15:4:1,22:2:1,15:4:1,23:4:1,15:4:1,22:2:1,15:4:1,23:4:1,15:4:1,22:2:1,15:4:1,23:4:1,15:4:1,22:2:1,
      22:2:1,23:4:1,7:4:2,23:4:1,22:2:1,23:4:1,7:4:2,23:4:1,22:2:1,23:4:1,7:4:2,23:4:1,22:2:1,23:4:1,7:4:2,23:4:1,22:2:1,23:4:1,7:4:2,23:4:1,22:2:1,23:4:1,7:4:2,23:4:1,22:2:1,23:4:1,7:4:2,23:4:1,22:2:1,23:4:1,7:4:2,23:4:1,22:2:1,23:4:1,7:4:2,23:4:1,22:2:1,23:4:1,7:4:2,23:4:1,22:2:1,23:4:1,7:4:2,23:4:1,22:2:1,23:4:1,7:4:2,23:4:1,22:2:1,
      22:2:1,15:4:1,23:4:1,15:4:1,22:2:1,15:4:1,23:4:1,15:4:1,22:2:1,15:4:1,23:4:1,15:4:1,22:2:1,15:4:1,23:4:1,15:4:1,22:2:1,15:4:1,23:4:1,15:4:1,22:2:1,15:4:1,23:4:1,15:4:1,22:2:1,15:4:1,23:4:1,15:4:1,22:2:1,15:4:1,23:4:1,15:4:1,22:2:1,15:4:1,23:4:1,15:4:1,22:2:1,15:4:1,23:4:1,15:4:1,22:2:1,15:4:1,23:4:1,15:4:1,22:2:1,15:4:1,23:4:1,15:4:1,22:2:1,
      22:2:1,22:2:1,22:2:1,22:2:1,8:4:2,22:2:1,22:2:1,22:2:1,8:4:2,22:2:1,22:2:1,22:2:1,8:4:2,22:2:1,22:2:1,22:2:1,8:4:2,22:2:1,22:2:1,22:2:1,8:4:2,22:2:1,22:2:1,22:2:1,8:4:2,22:2:1,22:2:1,22:2:1,8:4:2,22:2:1,22:2:1,22:2:1,8:4:2,22:2:1,22:2:1,22:2:1,8:4:2,22:2:1,22:2:1,22:2:1,8:4:2,22:2:1,22:2:1,22:2:1,8:4:2,22:2:1,22:2:1,22:2:1,22:2:1,
      22:2:1,15:4:1,23:4:1,15:4:1,22:2:1,15:4:1,23:4:1,15:4:1,22:2:1,15:4:1,23:4:1,15:4:1,22:2:1,15:4:1,23:4:1,15:4:1,22:2:1,15:4:1,23:4:1,15:4:1,22:2:1,15:4:1,23:4:1,15:4:1,22:2:1,15:4:1,23:4:1,15:4:1,22:2:1,15:4:1,23:4:1,15:4:1,22:2:1,15:4:1,23:4:1,15:4:1,22:2:1,15:4:1,23:4:1,15:4:1,22:2:1,15:4:1,23:4:1,15:4:1,22:2:1,15:4:1,23:4:1,15:4:1,22:2:1,
      22:2:1,23:4:1,7:4:2,23:4:1,22:2:1,23:4:1,7:4:2,23:4:1,22:2:1,23:4:1,7:4:2,23:4:1,22:2:1,23:4:1,7:4:2,23:4:1,22:2:1,23:4:1,7:4:2,23:4:1,22:2:1,23:4:1,7:4:2,23:4:1,22:2:1,23:4:1,7:4:2,23:4:1,22:2:1,23:4:1,7:4:2,23:4:1,22:2:1,23:4:1,7:4:2,23:4:1,22:2:1,23:4:1,7:4:2,23:4:1,22:2:1,23:4:1,7:4:2,23:4:1,22:2:1,23:4:1,7:4:2,23:4:1,22:2:1,
      22:2:1,15:4:1,23:4:1,15:4:1,22:2:1,15:4:1,23:4:1,15:4:1,22:2:1,15:4:1,23:4:1,15:4:1,22:2:1,15:4:1,23:4:1,15:4:1,22:2:1,15:4:1,23:4:1,15:4:1,22:2:1,15:4:1,23:4:1,15:4:1,22:2:1,15:4:1,23:4:1,15:4:1,22:2:1,15:4:1,23:4:1,15:4:1,22:2:1,15:4:1,23:4:1,15:4:1,22:2:1,15:4:1,23:4:1,15:4:1,22:2:1,15:4:1,23:4:1,15:4:1,22:2:1,15:4:1,23:4:1,15:4:1,22:2:1,
      22:1:1,22:2:1,22:2:1,22:2:1,22:2:1,22:2:1,22:2:1,22:2:1,22:2:1,22:2:1,22:2:1,22:2:1,22:2:1,22:2:1,22:2:1,22:2:1,22:2:1,22:2:1,22:2:1,22:2:1,22:2:1,22:2:1,22:2:1,22:2:1,22:2:1,22:2:1,22:2:1,22:2:1,22:2:1,22:2:1,22:2:1,22:2:1,22:2:1,22:2:1,22:2:1,22:2:1,22:2:1,22:2:1,22:2:1,22:2:1,22:2:1,22:2:1,22:2:1,22:2:1,22:2:1,22:2:1,22:2:1,22:2:1,22:1:1
    </Custom2DField>
  </Connectivity>
  <PhysicsAttributes inertiaTensor="7.70067,0,0,0,38.40001,0,0,0,30.74067" centerOfMass="9.2,0.249,-4.4" mass="1" frictionType="0"/>
  <Bounding>
    <AABB minX="-0.4" minY="0" minZ="-9.2" maxX="18.8" maxY="0.498" maxZ="0.400001"/>
  </Bounding>
  <GeometryBounding>
    <AABB minX="-0.4" minY="0" minZ="-9.2" maxX="18.8" maxY="0.498" maxZ="0.4"/>
  </GeometryBounding>
</LEGOPrimitive>
