<?xml version="1.0" encoding="UTF-8" standalone="no" ?>
<LEGOPrimitive versionMajor="1" versionMinor="0">
  <Annotations>
    <Annotation aliases="18855"/>
    <Annotation designname="FEEDING BOTTLE W. 3,2 SHAFT"/>
    <Annotation maingroupid="246"/>
    <Annotation maingroupname="FIGURE ACCESSORIES IN HAND"/>
    <Annotation platformid="200"/>
    <Annotation platformname="SYSTEM"/>
    <Annotation version="1"/>
  </Annotations>
  <Collision>
    <Box sX="0.224188" sY="0.217033" sZ="0.219075" angle="45" ax="0" ay="1" az="0" tx="-0.001592" ty="1.00696" tz="-0.003616"/>
    <Box sX="0.128774" sY="0.280797" sZ="0.064635" angle="0" ax="0" ay="1" az="0" tx="-0.138774" ty="0.582834" tz="0"/>
    <Box sX="0.156332" sY="0.484869" sZ="0.191221" angle="90" ax="0" ay="1" az="0" tx="0.098009" ty="0.494869" tz="0"/>
    <Box sX="0.131248" sY="0.484869" sZ="0.285526" angle="0" ax="0" ay="1" az="0" tx="0.038015" ty="0.494869" tz="-0.000481"/>
    <Box sX="0.103397" sY="0.068343" sZ="0.103397" angle="45" ax="0" ay="1" az="0" tx="0" ty="1.31234" tz="-0.002213"/>
    <Box sX="0.062622" sY="0.076814" sZ="0.062622" angle="45" ax="0" ay="1" az="0" tx="0" ty="1.47083" tz="-0.002213"/>
    <Box sX="0.098744" sY="0.229561" sZ="0.098744" angle="45" ax="0" ay="1" az="0" tx="-0.399467" ty="0.54037" tz="-0.000565"/>
    <Box sX="0.224188" sY="0.140404" sZ="0.219075" angle="45" ax="0" ay="1" az="0" tx="-0.001592" ty="0.150404" tz="-0.003616"/>
  </Collision>
  <Connectivity>
    <Custom2DField type="22" width="2" height="2" angle="0" ax="0" ay="1" az="0" tx="-0.4" ty="0" tz="-0.4">
      29:0,29:0,29:0,
      29:0,5:4:34,29:0,
      29:0,29:0,29:0
    </Custom2DField>
    <Axel type="7" length="0.479123" requireGrabbing="1" startCapped="1" endCapped="1" angle="0" ax="0" ay="0" az="1" tx="-0.400467" ty="0.300809" tz="-0.000565"/>
  </Connectivity>
  <PhysicsAttributes inertiaTensor="0.241333,0,0,0,0.101753,0,0,0,0.271244" centerOfMass="-0.115058,0.785008,0" mass="1" frictionType="0"/>
  <Bounding>
    <AABB minX="-0.559462" minY="0" minZ="-0.328273" maxX="0.329346" maxY="1.57002" maxZ="0.328273"/>
  </Bounding>
  <GeometryBounding>
    <AABB minX="-0.559462" minY="0" minZ="-0.328273" maxX="0.329346" maxY="1.57002" maxZ="0.328273"/>
  </GeometryBounding>
</LEGOPrimitive>
