<?xml version="1.0" encoding="UTF-8" standalone="no" ?>
<LEGOPrimitive versionMajor="1" versionMinor="0">
  <Annotations>
    <Annotation aliases="24309"/>
    <Annotation designname="Brick w/half bow 2x3 w/cut"/>
    <Annotation maingroupid="207"/>
    <Annotation maingroupname="BRICKS WITH BOWS AND ARCHES"/>
    <Annotation platformid="200"/>
    <Annotation platformname="SYSTEM"/>
    <Annotation version="1"/>
  </Annotations>
  <Collision>
    <Box sX="0.79" sY="0.79" sZ="0.09" angle="120" ax="0.57735" ay="-0.57735" az="0.577351" tx="1.2" ty="-0.22" tz="-0.4"/>
    <Box sX="0.79" sY="0.61635" sZ="0.208698" angle="120" ax="0.57735" ay="-0.57735" az="0.577351" tx="0.22635" ty="0.218697" tz="-0.4"/>
    <Box sX="0.79" sY="0.2045" sZ="0.070043" angle="120.00001" ax="0.57735" ay="-0.57735" az="0.577351" tx="-0.1855" ty="0.534796" tz="-0.4"/>
    <Box sX="0.79" sY="0.506944" sZ="0.268204" angle="120" ax="0.57735" ay="-0.57735" az="0.577351" tx="0.916944" ty="-0.041797" tz="-0.4"/>
    <Box sX="0.79" sY="0.38437" sZ="0.066695" angle="113.46696" ax="0.533671" ay="-0.656041" az="0.533671" tx="0.429075" ty="0.454851" tz="-0.4"/>
    <Box sX="0.79" sY="0.308135" sZ="0.066695" angle="109.22094" ax="0.497668" ay="-0.710388" az="0.497669" tx="1.11805" ty="0.277312" tz="-0.4"/>
    <Box sX="0.79" sY="0.335543" sZ="0.066695" angle="103.32388" ax="0.432773" ay="-0.790832" az="0.432773" tx="1.66562" ty="-4.5E-005" tz="-0.4"/>
  </Collision>
  <Connectivity>
    <Custom2DField type="22" width="2" height="4" angle="0" ax="0" ay="1" az="0" tx="-0.4" ty="0" tz="-1.2">
      22:1:1,22:2:1,22:1:1,
      22:2:1,15:4:1,22:2:1,
      22:2:1,9:4:1,22:2:1,
      22:2:1,15:4:1,22:2:1,
      22:1:1,22:2:1,22:1:1
    </Custom2DField>
    <Custom2DField type="22" width="4" height="4" angle="0" ax="0" ay="1" az="0" tx="0.4" ty="-0.32" tz="-1.2">
      22:1:1,22:2:1,22:2:1,22:2:1,22:1:1,
      22:2:1,15:4:1,23:4:1,15:4:1,22:2:1,
      22:2:1,23:4:1,7:4:1,23:4:1,22:2:1,
      22:2:1,15:4:1,23:4:1,15:4:1,22:2:1,
      22:1:1,22:2:1,22:2:1,22:2:1,22:1:1
    </Custom2DField>
  </Connectivity>
  <PhysicsAttributes inertiaTensor="0.290133,0,0,0,0.693333,0,0,0,0.5568" centerOfMass="0.8,0.16,-0.4" mass="1" frictionType="0"/>
  <Bounding>
    <AABB minX="-0.4" minY="-0.32" minZ="-1.2" maxX="2" maxY="0.64" maxZ="0.4"/>
  </Bounding>
  <GeometryBounding>
    <AABB minX="-0.4" minY="-0.32" minZ="-1.2" maxX="2" maxY="0.64" maxZ="0.4"/>
  </GeometryBounding>
</LEGOPrimitive>
