<?xml version="1.0" encoding="UTF-8" standalone="no" ?>
<LEGOPrimitive versionMajor="1" versionMinor="0">
  <Annotations>
    <Annotation aliases="41750;42020"/>
    <Annotation designname="LEFT SHELL 3X8X2 W/BOW/ANGLE"/>
    <Annotation maingroupid="208"/>
    <Annotation maingroupname="BRICKS WITH SPECIAL BOWS AND ANGLES"/>
    <Annotation platformid="200"/>
    <Annotation platformname="SYSTEM"/>
    <Annotation version="5"/>
  </Annotations>
  <Collision>
    <Box sX="0.048659" sY="0.305685" sZ="0.09" angle="148.65384" ax="-0.28058" ay="-0.678703" az="-0.678703" tx="0.442639" ty="0.1" tz="1.15748"/>
    <Box sX="0.371098" sY="0.4582" sZ="0.007708" angle="120.62015" ax="-0.014192" ay="-0.569721" az="-0.821716" tx="0.583564" ty="0.493275" tz="0.881272"/>
    <Box sX="0.048659" sY="0.147741" sZ="0.09" angle="148.65382" ax="-0.28058" ay="-0.678703" az="-0.678703" tx="-0.244729" ty="0.1" tz="0.468214"/>
    <Box sX="0.390445" sY="0.944817" sZ="0.09" angle="115.79841" ax="-0.552476" ay="-0.625727" az="-0.550669" tx="3.4667" ty="1.69995" tz="0.003199"/>
    <Box sX="0.390445" sY="0.954265" sZ="0.09" angle="108.3386" ax="-0.491296" ay="-0.720623" az="-0.489214" tx="1.64708" ty="1.23054" tz="0.008735"/>
    <Box sX="0.855065" sY="0.857618" sZ="0.041131" angle="100.3887" ax="-0.488108" ay="-0.513096" az="-0.706033" tx="3.438" ty="1.32557" tz="1.13135"/>
    <Box sX="0.855065" sY="0.746438" sZ="0.01764" angle="89.58376" ax="-0.40291" ay="-0.613927" az="-0.678791" tx="1.81525" ty="0.935614" tz="1.18038"/>
    <Box sX="0.777327" sY="0.390001" sZ="0.47" angle="180" ax="0" ay="0.707107" az="0.707107" tx="5.21267" ty="1.44" tz="0"/>
    <Box sX="0.789999" sY="0.79" sZ="0.085996" angle="180" ax="0" ay="0.707107" az="0.707107" tx="5.2" ty="1.056" tz="1.2"/>
    <Box sX="0.790001" sY="0.892278" sZ="0.085996" angle="180" ax="0" ay="0.537009" az="0.843576" tx="5.2" ty="1.45491" tz="1.14189"/>
    <Box sX="0.776182" sY="0.39" sZ="0.271388" angle="180" ax="0" ay="0.707107" az="0.707107" tx="5.21382" ty="1.24139" tz="0.806397"/>
    <Box sX="0.431262" sY="0.39" sZ="0.268392" angle="171.21306" ax="0.076831" ay="-0.705017" az="-0.705017" tx="0.660599" ty="0.414862" tz="0"/>
    <Box sX="0.882975" sY="0.065" sZ="0.391886" angle="175.69824" ax="0.035219" ay="-0.703497" az="-0.709825" tx="3.58873" ty="1.33028" tz="-0.327018"/>
    <Box sX="1.13529" sY="0.065" sZ="0.368838" angle="163.76837" ax="0.141214" ay="-0.69668" az="-0.703346" tx="1.7712" ty="0.871394" tz="-0.324203"/>
    <Box sX="0.790001" sY="0.39" sZ="0.09" angle="180" ax="0" ay="0.707107" az="0.707107" tx="0.4" ty="0.1" tz="0"/>
    <Box sX="0.390445" sY="0.667594" sZ="0.108758" angle="102.35323" ax="-0.422429" ay="-0.80298" az="-0.420448" tx="0.225933" ty="0.488148" tz="-0.001538"/>
    <Box sX="0.048659" sY="0.071835" sZ="0.09" angle="148.65379" ax="-0.28058" ay="-0.678703" az="-0.678703" tx="1.07751" ty="0.1" tz="1.79189"/>
    <Box sX="0.065" sY="0.932156" sZ="0.195558" angle="180" ax="0" ay="0.707107" az="0.707107" tx="1.125" ty="0.205557" tz="0.542156"/>
  </Collision>
  <Connectivity>
    <Custom2DField type="22" width="4" height="6" angle="0" ax="0" ay="1" az="0" tx="-0.4" ty="0" tz="-0.4">
      22:1:1,22:2:1,22:2:1,22:2:1,22:1:1,
      22:2:1,15:4:1,22:2:1,15:4:1,22:2:1,
      22:1:1,22:2:1,22:2:1,22:2:1,22:2:1,
      29:0:1,29:0:1,29:0:1,29:0:1,22:2:1,
      29:0:1,29:0:1,22:2:1,29:0:1,22:2:1,
      29:0:1,29:0:1,29:0:1,29:0:1,22:2:1,
      29:0:1,29:0:1,29:0:1,29:0:1,22:1:1
    </Custom2DField>
    <Custom2DField type="22" width="4" height="6" angle="0" ax="0" ay="1" az="0" tx="4.4" ty="0.96" tz="-0.4">
      22:1:1,22:2:1,22:2:1,22:2:1,22:1:1,
      22:2:1,15:4:1,23:4:1,15:4:1,22:2:1,
      22:2:1,23:4:1,7:4:2,23:4:1,22:2:1,
      22:2:1,15:4:1,23:4:1,15:4:1,22:2:1,
      22:2:1,23:4:1,7:4:2,23:4:1,22:2:1,
      22:2:1,15:4:1,23:4:1,15:4:1,22:2:1,
      22:1:1,22:2:1,22:2:1,22:2:1,22:1:1
    </Custom2DField>
    <Custom2DField type="23" width="4" height="2" angle="0" ax="0" ay="1" az="0" tx="4.4" ty="1.92" tz="-0.4">
      18:1:1,23:4:1,18:2:1,23:4:1,18:1:1,
      23:4:1,0:4:1,23:4:1,0:4:1,23:4:1,
      18:1:1,23:4:1,18:2:1,23:4:1,18:1:1
    </Custom2DField>
  </Connectivity>
  <PhysicsAttributes inertiaTensor="2.78881,0,0,0,14.95718,0,0,0,14.08838" centerOfMass="3.14475,1.13221,0.480016" mass="3.51999998093" frictionType="0"/>
  <Bounding>
    <AABB minX="-0.4" minY="0" minZ="-0.4" maxX="6" maxY="2.0981" maxZ="2"/>
  </Bounding>
  <GeometryBounding>
    <AABB minX="-0.4" minY="0" minZ="-0.4" maxX="6" maxY="2.0981" maxZ="2"/>
  </GeometryBounding>
</LEGOPrimitive>
