<?xml version="1.0" encoding="UTF-8" standalone="no" ?>
<LEGOPrimitive versionMajor="1" versionMinor="0">
  <Annotations>
    <Annotation aliases="98147"/>
    <Annotation designname="MINI HEAD FANGPYRE"/>
    <Annotation maingroupid="242"/>
    <Annotation maingroupname="FIGURE, HEADS AND MASKS"/>
    <Annotation platformid="200"/>
    <Annotation platformname="SYSTEM"/>
    <Annotation version="2"/>
  </Annotations>
  <Collision>
    <Box sX="0.055175" sY="0.285745" sZ="0.064197" angle="0" ax="0" ay="1" az="0" tx="0" ty="0.302734" tz="-0.330341"/>
    <Box sX="0.055175" sY="0.285745" sZ="0.064197" angle="0" ax="0" ay="1" az="0" tx="-0.321226" ty="0.31926" tz="-0.000797"/>
    <Box sX="0.055175" sY="0.285745" sZ="0.064197" angle="0" ax="0" ay="1" az="0" tx="0.331109" ty="0.31926" tz="-0.000797"/>
    <Box sX="0.446606" sY="0.278736" sZ="0.036769" angle="0" ax="0" ay="1" az="0" tx="0" ty="0.289148" tz="0.290001"/>
    <Box sX="0.114753" sY="0.094197" sZ="0.068299" angle="0" ax="0" ay="1" az="0" tx="-0.007317" ty="-0.656653" tz="-0.493103"/>
    <Box sX="0.227115" sY="0.145549" sZ="0.083064" angle="0" ax="0" ay="1" az="0" tx="-0.00878" ty="-0.382818" tz="-0.508606"/>
    <Box sX="0.259932" sY="0.170976" sZ="0.44855" angle="22.91316" ax="-0.416721" ay="-0.100808" az="-0.903427" tx="0.854257" ty="1.42307" tz="0.614045"/>
    <Box sX="0.196941" sY="0.20341" sZ="0.482493" angle="33.1005" ax="-0.310667" ay="0.712153" az="0.629543" tx="-0.620039" ty="0.901214" tz="0.935568"/>
    <Box sX="0.120292" sY="0.150077" sZ="0.482493" angle="29.47963" ax="-0.803559" ay="-0.589225" az="0.084306" tx="-0.656042" ty="0.568826" tz="0.079731"/>
    <Box sX="0.200506" sY="0.205286" sZ="0.523628" angle="38.28911" ax="-0.952381" ay="0.289499" az="-0.095715" tx="0.679385" ty="1.05882" tz="0.014055"/>
    <Box sX="0.088521" sY="0.257499" sZ="0.290992" angle="0" ax="0" ay="1" az="0" tx="0.499577" ty="0.65395" tz="-0.214026"/>
    <Box sX="0.50145" sY="0.051028" sZ="0.245758" angle="11.74861" ax="0" ay="1" az="0" tx="0.0519" ty="0.663579" tz="-0.157195"/>
    <Box sX="0.442197" sY="0.404097" sZ="0.04085" angle="0" ax="0" ay="1" az="0" tx="-0.002927" ty="0.102529" tz="-0.461245"/>
    <Box sX="0.027713" sY="0.207988" sZ="0.348243" angle="0" ax="0" ay="1" az="0" tx="-0.477619" ty="0.217885" tz="-0.062048"/>
    <Box sX="0.038694" sY="0.207988" sZ="0.334629" angle="0" ax="0" ay="1" az="0" tx="0.463285" ty="0.217885" tz="-0.075661"/>
  </Collision>
  <Connectivity>
    <Custom2DField type="22" width="2" height="2" angle="0" ax="0" ay="1" az="0" tx="-0.4" ty="0" tz="-0.4">
      29:0,29:0,29:0,
      29:0,15:4:32,29:0,
      29:0,29:0,29:0
    </Custom2DField>
    <Hinge type="200" oriented="1" angle="0" ax="0" ay="0" az="1" tx="0" ty="0" tz="0"/>
  </Connectivity>
  <PhysicsAttributes inertiaTensor="0.542716,0,0,0,0.661666,0,0,0,0.658821" centerOfMass="0.074368,0.682932,0.146887" mass="1.20000004768" frictionType="0"/>
  <Bounding>
    <AABB minX="-1.03767" minY="-0.780447" minZ="-0.693515" maxX="1.27021" maxY="1.81352" maxZ="1.47335"/>
  </Bounding>
  <GeometryBounding>
    <AABB minX="-1.00023" minY="-0.780447" minZ="-0.693515" maxX="1.27021" maxY="1.81352" maxZ="1.41228"/>
  </GeometryBounding>
</LEGOPrimitive>
